nmtvis/AttentionVisualizer.py
nmtvis/BeamSearchVisualizer.py
nmtvis/EmbeddingVisualizer.py
nmtvis/__init__.py
nmtvis/call_html.py
nmtvis/get_beam_dependency.py
nmtvis/get_dependency.py
nmtvis/get_embedding_dependency.py
nmtvis/process_data.py
nmtvis-1.6.dist-info/LICENSE
nmtvis-1.6.dist-info/METADATA
nmtvis-1.6.dist-info/WHEEL
nmtvis-1.6.dist-info/top_level.txt
nmtvis-1.6.dist-info/RECORD
