Metadata-Version: 2.1
Name: nmtvis
Version: 1.6
Summary: A visualization toolkit for NMT(Neural Machine Translation) system.
Home-page: https://github.com/player-eric/NMT-Visualizer
Author: Player Eric
Author-email: digimonyan@gmail.com
License: MIT
Platform: UNKNOWN
Classifier: Environment :: Web Environment
Classifier: Intended Audience :: Developers
Classifier: Operating System :: OS Independent
Classifier: Topic :: Utilities
Classifier: Topic :: Software Development :: Libraries :: Python Modules
Classifier: Programming Language :: Python
Requires-Dist: numpy
Requires-Dist: sklearn
